driftdeck/__init__.py
driftdeck/__main__.py
driftdeck/core.py
driftdeck/httpd.py
driftdeck/slide.html
driftdeck/style.css
driftdeck-0.3.3.dist-info/entry_points.txt
driftdeck-0.3.3.dist-info/LICENSE
driftdeck-0.3.3.dist-info/WHEEL
driftdeck-0.3.3.dist-info/METADATA
driftdeck-0.3.3.dist-info/RECORD
