Metadata-Version: 2.1
Name: driftdeck
Version: 0.3.3
Summary: Drift Deck eats markdown files and spits out beautiful slides directly into your browser.
Home-page: https://gitlab.com/XenGi/driftdeck
License: MIT
Keywords: markdown,slides,browser
Author: Ricardo Band
Author-email: email@ricardo.band
Requires-Python: >=3.4,<4.0
Classifier: Development Status :: 4 - Beta
Classifier: Environment :: Console
Classifier: Intended Audience :: Developers
Classifier: Intended Audience :: Education
Classifier: Intended Audience :: End Users/Desktop
Classifier: Intended Audience :: Information Technology
Classifier: Intended Audience :: Science/Research
Classifier: Intended Audience :: System Administrators
Classifier: License :: OSI Approved :: MIT License
Classifier: Natural Language :: English
Classifier: Operating System :: OS Independent
Classifier: Programming Language :: Python :: 3
Classifier: Programming Language :: Python :: 3.4
Classifier: Programming Language :: Python :: 3.5
Classifier: Programming Language :: Python :: 3.6
Classifier: Programming Language :: Python :: 3.7
Classifier: Topic :: Communications
Classifier: Topic :: Education
Classifier: Topic :: Multimedia :: Graphics :: Presentation
Classifier: Topic :: Text Processing :: Markup
Requires-Dist: docopt (>=0.6,<0.7)
Requires-Dist: markdown (>=3.0,<4.0)
Project-URL: Repository, https://gitlab.com/XenGi/driftdeck
